<class type="cobiscorp.ecobis.censervicegenerator.dto.model.SGProcedureMapping" id="1"><class type="cobiscorp.ecobis.censervicegenerator.dto.model.SGProcedureBase" id="2" name="storedProcedure"><field type="String" name="database" value="cob_bvirtual" /><field type="String" name="name" value="sp_tr14_apertura_CDP" /><field type="String" name="version" value="1" /></class><field type="String" name="procedureName" value="cob_bvirtual..sp_tr14_apertura_CDP" /><collection type="List" length="46" id="3" name="parameters"><class type="cobiscorp.ecobis.censervicegenerator.dto.model.SGProcedureMappingParameter" id="4" index="0"><class type="cobiscorp.ecobis.censervicegenerator.dto.model.SGProcedureParameter" id="5" name="parameter"><field type="String" name="name" value="@i_capitaliza" /><field type="String" name="dataType" value="char" /><field type="String" name="direction" value="in" /></class><field type="String" name="mappingTypeName" value="DTO" /><field type="String" name="mappingDirection" value="in" /><field type="String" name="dTOAlias" value="inCertificateDeposit" /><field type="String" name="dTOPropertyName" value="capitalize" /><field type="String" name="cTSDataType" value="SQLCHAR" /><field type="boolean" name="allowNull" value="false" /></class><class type="cobiscorp.ecobis.censervicegenerator.dto.model.SGProcedureMappingParameter" id="6" index="1"><class type="cobiscorp.ecobis.censervicegenerator.dto.model.SGProcedureParameter" id="7" name="parameter"><field type="String" name="name" value="@i_cedula1" /><field type="String" name="dataType" value="varchar" /><field type="String" name="direction" value="in" /></class><field type="String" name="mappingTypeName" value="DTO" /><field type="String" name="mappingDirection" value="in" /><field type="String" name="dTOAlias" value="inBeneficiaryCertificateDeposit" /><field type="String" name="dTOPropertyName" value="cedula1" /><field type="String" name="cTSDataType" value="SQLVARCHAR" /><field type="boolean" name="allowNull" value="false" /></class><class type="cobiscorp.ecobis.censervicegenerator.dto.model.SGProcedureMappingParameter" id="8" index="2"><class type="cobiscorp.ecobis.censervicegenerator.dto.model.SGProcedureParameter" id="9" name="parameter"><field type="String" name="name" value="@i_cedula2" /><field type="String" name="dataType" value="varchar" /><field type="String" name="direction" value="in" /></class><field type="String" name="mappingTypeName" value="DTO" /><field type="String" name="mappingDirection" value="in" /><field type="String" name="dTOAlias" value="inBeneficiaryCertificateDeposit" /><field type="String" name="dTOPropertyName" value="cedula2" /><field type="String" name="cTSDataType" value="SQLVARCHAR" /><field type="boolean" name="allowNull" value="false" /></class><class type="cobiscorp.ecobis.censervicegenerator.dto.model.SGProcedureMappingParameter" id="10" index="3"><class type="cobiscorp.ecobis.censervicegenerator.dto.model.SGProcedureParameter" id="11" name="parameter"><field type="String" name="name" value="@i_cedula3" /><field type="String" name="dataType" value="varchar" /><field type="String" name="direction" value="in" /></class><field type="String" name="mappingTypeName" value="DTO" /><field type="String" name="mappingDirection" value="in" /><field type="String" name="dTOAlias" value="inBeneficiaryCertificateDeposit" /><field type="String" name="dTOPropertyName" value="cedula3" /><field type="String" name="cTSDataType" value="SQLVARCHAR" /><field type="boolean" name="allowNull" value="false" /></class><class type="cobiscorp.ecobis.censervicegenerator.dto.model.SGProcedureMappingParameter" id="12" index="4"><class type="cobiscorp.ecobis.censervicegenerator.dto.model.SGProcedureParameter" id="13" name="parameter"><field type="String" name="name" value="@i_cedula4" /><field type="String" name="dataType" value="varchar" /><field type="String" name="direction" value="in" /></class><field type="String" name="mappingTypeName" value="DTO" /><field type="String" name="mappingDirection" value="in" /><field type="String" name="dTOAlias" value="inBeneficiaryCertificateDeposit" /><field type="String" name="dTOPropertyName" value="cedula4" /><field type="String" name="cTSDataType" value="SQLVARCHAR" /><field type="boolean" name="allowNull" value="false" /></class><class type="cobiscorp.ecobis.censervicegenerator.dto.model.SGProcedureMappingParameter" id="14" index="5"><class type="cobiscorp.ecobis.censervicegenerator.dto.model.SGProcedureParameter" id="15" name="parameter"><field type="String" name="name" value="@i_cta_debito" /><field type="String" name="dataType" value="varchar" /><field type="String" name="direction" value="in" /></class><field type="String" name="mappingTypeName" value="DTO" /><field type="String" name="mappingDirection" value="in" /><field type="String" name="dTOAlias" value="inProduct" /><field type="String" name="dTOPropertyName" value="productNumber" /><field type="String" name="cTSDataType" value="SQLVARCHAR" /><field type="boolean" name="allowNull" value="false" /></class><class type="cobiscorp.ecobis.censervicegenerator.dto.model.SGProcedureMappingParameter" id="16" index="6"><class type="cobiscorp.ecobis.censervicegenerator.dto.model.SGProcedureParameter" id="17" name="parameter"><field type="String" name="name" value="@i_dia_pago" /><field type="String" name="dataType" value="tinyint" /><field type="String" name="direction" value="in" /></class><field type="String" name="mappingTypeName" value="DTO" /><field type="String" name="mappingDirection" value="in" /><field type="String" name="dTOAlias" value="inCertificateDeposit" /><field type="String" name="dTOPropertyName" value="payDay" /><field type="String" name="cTSDataType" value="SQLINT1" /><field type="boolean" name="allowNull" value="false" /></class><class type="cobiscorp.ecobis.censervicegenerator.dto.model.SGProcedureMappingParameter" id="18" index="7"><class type="cobiscorp.ecobis.censervicegenerator.dto.model.SGProcedureParameter" id="19" name="parameter"><field type="String" name="name" value="@i_doble_autorizacion" /><field type="String" name="dataType" value="char" /><field type="String" name="direction" value="in" /></class><field type="String" name="mappingTypeName" value="DTO" /><field type="String" name="mappingDirection" value="in" /><field type="String" name="dTOAlias" value="inTransactionContextCIB" /><field type="String" name="dTOPropertyName" value="authenticationRequired" /><field type="String" name="cTSDataType" value="SQLCHAR" /><field type="boolean" name="allowNull" value="false" /></class><class type="cobiscorp.ecobis.censervicegenerator.dto.model.SGProcedureMappingParameter" id="20" index="8"><class type="cobiscorp.ecobis.censervicegenerator.dto.model.SGProcedureParameter" id="21" name="parameter"><field type="String" name="name" value="@i_ente" /><field type="String" name="dataType" value="int" /><field type="String" name="direction" value="in" /></class><field type="String" name="mappingTypeName" value="DTO" /><field type="String" name="mappingDirection" value="in" /><field type="String" name="dTOAlias" value="inUser" /><field type="String" name="dTOPropertyName" value="entityId" /><field type="String" name="cTSDataType" value="SQLINT4" /><field type="boolean" name="allowNull" value="false" /></class><class type="cobiscorp.ecobis.censervicegenerator.dto.model.SGProcedureMappingParameter" id="22" index="9"><class type="cobiscorp.ecobis.censervicegenerator.dto.model.SGProcedureParameter" id="23" name="parameter"><field type="String" name="name" value="@i_fecha_valor" /><field type="String" name="dataType" value="datetime" /><field type="String" name="direction" value="in" /></class><field type="String" name="mappingTypeName" value="DTO" /><field type="String" name="mappingDirection" value="in" /><field type="String" name="dTOAlias" value="inCertificateDeposit" /><field type="String" name="dTOPropertyName" value="processDate" /><field type="String" name="cTSDataType" value="SQLDATETIME" /><field type="boolean" name="allowNull" value="false" /></class><class type="cobiscorp.ecobis.censervicegenerator.dto.model.SGProcedureMappingParameter" id="24" index="10"><class type="cobiscorp.ecobis.censervicegenerator.dto.model.SGProcedureParameter" id="25" name="parameter"><field type="String" name="name" value="@i_forma_pago" /><field type="String" name="dataType" value="char" /><field type="String" name="direction" value="in" /></class><field type="String" name="mappingTypeName" value="DTO" /><field type="String" name="mappingDirection" value="in" /><field type="String" name="dTOAlias" value="inCertificateDeposit" /><field type="String" name="dTOPropertyName" value="methodOfPayment" /><field type="String" name="cTSDataType" value="SQLCHAR" /><field type="boolean" name="allowNull" value="false" /></class><class type="cobiscorp.ecobis.censervicegenerator.dto.model.SGProcedureMappingParameter" id="26" index="11"><class type="cobiscorp.ecobis.censervicegenerator.dto.model.SGProcedureParameter" id="27" name="parameter"><field type="String" name="name" value="@i_login" /><field type="String" name="dataType" value="varchar" /><field type="String" name="direction" value="in" /></class><field type="String" name="mappingTypeName" value="DTO" /><field type="String" name="mappingDirection" value="in" /><field type="String" name="dTOAlias" value="inUser" /><field type="String" name="dTOPropertyName" value="name" /><field type="String" name="cTSDataType" value="SQLVARCHAR" /><field type="boolean" name="allowNull" value="false" /></class><class type="cobiscorp.ecobis.censervicegenerator.dto.model.SGProcedureMappingParameter" id="28" index="12"><class type="cobiscorp.ecobis.censervicegenerator.dto.model.SGProcedureParameter" id="29" name="parameter"><field type="String" name="name" value="@i_mail" /><field type="String" name="dataType" value="varchar" /><field type="String" name="direction" value="in" /></class><field type="String" name="mappingTypeName" value="DTO" /><field type="String" name="mappingDirection" value="in" /><field type="String" name="dTOAlias" value="inCertificateDeposit" /><field type="String" name="dTOPropertyName" value="mail" /><field type="String" name="cTSDataType" value="SQLVARCHAR" /><field type="boolean" name="allowNull" value="false" /></class><class type="cobiscorp.ecobis.censervicegenerator.dto.model.SGProcedureMappingParameter" id="30" index="13"><class type="cobiscorp.ecobis.censervicegenerator.dto.model.SGProcedureParameter" id="31" name="parameter"><field type="String" name="name" value="@i_moneda" /><field type="String" name="dataType" value="smallint" /><field type="String" name="direction" value="in" /></class><field type="String" name="mappingTypeName" value="DTO" /><field type="String" name="mappingDirection" value="in" /><field type="String" name="dTOAlias" value="inProduct" /><field type="String" name="dTOPropertyName" value="currencyId" /><field type="String" name="cTSDataType" value="SQLINT2" /><field type="boolean" name="allowNull" value="false" /></class><class type="cobiscorp.ecobis.censervicegenerator.dto.model.SGProcedureMappingParameter" id="32" index="14"><class type="cobiscorp.ecobis.censervicegenerator.dto.model.SGProcedureParameter" id="33" name="parameter"><field type="String" name="name" value="@i_monto" /><field type="String" name="dataType" value="float" /><field type="String" name="direction" value="in" /></class><field type="String" name="mappingTypeName" value="DTO" /><field type="String" name="mappingDirection" value="in" /><field type="String" name="dTOAlias" value="inCertificateDeposit" /><field type="String" name="dTOPropertyName" value="amount" /><field type="String" name="cTSDataType" value="SQLFLT8i" /><field type="boolean" name="allowNull" value="false" /></class><class type="cobiscorp.ecobis.censervicegenerator.dto.model.SGProcedureMappingParameter" id="34" index="15"><class type="cobiscorp.ecobis.censervicegenerator.dto.model.SGProcedureParameter" id="35" name="parameter"><field type="String" name="name" value="@i_nemonico" /><field type="String" name="dataType" value="varchar" /><field type="String" name="direction" value="in" /></class><field type="String" name="mappingTypeName" value="DTO" /><field type="String" name="mappingDirection" value="in" /><field type="String" name="dTOAlias" value="inCertificateDeposit" /><field type="String" name="dTOPropertyName" value="nemonic" /><field type="String" name="cTSDataType" value="SQLVARCHAR" /><field type="boolean" name="allowNull" value="false" /></class><class type="cobiscorp.ecobis.censervicegenerator.dto.model.SGProcedureMappingParameter" id="36" index="16"><class type="cobiscorp.ecobis.censervicegenerator.dto.model.SGProcedureParameter" id="37" name="parameter"><field type="String" name="name" value="@i_nombre1" /><field type="String" name="dataType" value="varchar" /><field type="String" name="direction" value="in" /></class><field type="String" name="mappingTypeName" value="DTO" /><field type="String" name="mappingDirection" value="in" /><field type="String" name="dTOAlias" value="inBeneficiaryCertificateDeposit" /><field type="String" name="dTOPropertyName" value="name1" /><field type="String" name="cTSDataType" value="SQLVARCHAR" /><field type="boolean" name="allowNull" value="false" /></class><class type="cobiscorp.ecobis.censervicegenerator.dto.model.SGProcedureMappingParameter" id="38" index="17"><class type="cobiscorp.ecobis.censervicegenerator.dto.model.SGProcedureParameter" id="39" name="parameter"><field type="String" name="name" value="@i_nombre2" /><field type="String" name="dataType" value="varchar" /><field type="String" name="direction" value="in" /></class><field type="String" name="mappingTypeName" value="DTO" /><field type="String" name="mappingDirection" value="in" /><field type="String" name="dTOAlias" value="inBeneficiaryCertificateDeposit" /><field type="String" name="dTOPropertyName" value="name2" /><field type="String" name="cTSDataType" value="SQLVARCHAR" /><field type="boolean" name="allowNull" value="false" /></class><class type="cobiscorp.ecobis.censervicegenerator.dto.model.SGProcedureMappingParameter" id="40" index="18"><class type="cobiscorp.ecobis.censervicegenerator.dto.model.SGProcedureParameter" id="41" name="parameter"><field type="String" name="name" value="@i_nombre3" /><field type="String" name="dataType" value="varchar" /><field type="String" name="direction" value="in" /></class><field type="String" name="mappingTypeName" value="DTO" /><field type="String" name="mappingDirection" value="in" /><field type="String" name="dTOAlias" value="inBeneficiaryCertificateDeposit" /><field type="String" name="dTOPropertyName" value="name3" /><field type="String" name="cTSDataType" value="SQLVARCHAR" /><field type="boolean" name="allowNull" value="false" /></class><class type="cobiscorp.ecobis.censervicegenerator.dto.model.SGProcedureMappingParameter" id="42" index="19"><class type="cobiscorp.ecobis.censervicegenerator.dto.model.SGProcedureParameter" id="43" name="parameter"><field type="String" name="name" value="@i_nombre4" /><field type="String" name="dataType" value="varchar" /><field type="String" name="direction" value="in" /></class><field type="String" name="mappingTypeName" value="DTO" /><field type="String" name="mappingDirection" value="in" /><field type="String" name="dTOAlias" value="inBeneficiaryCertificateDeposit" /><field type="String" name="dTOPropertyName" value="name4" /><field type="String" name="cTSDataType" value="SQLVARCHAR" /><field type="boolean" name="allowNull" value="false" /></class><class type="cobiscorp.ecobis.censervicegenerator.dto.model.SGProcedureMappingParameter" id="44" index="20"><class type="cobiscorp.ecobis.censervicegenerator.dto.model.SGProcedureParameter" id="45" name="parameter"><field type="String" name="name" value="@i_oficina" /><field type="String" name="dataType" value="smallint" /><field type="String" name="direction" value="in" /></class><field type="String" name="mappingTypeName" value="DTO" /><field type="String" name="mappingDirection" value="in" /><field type="String" name="dTOAlias" value="inCertificateDeposit" /><field type="String" name="dTOPropertyName" value="office" /><field type="String" name="cTSDataType" value="SQLINT2" /><field type="boolean" name="allowNull" value="false" /></class><class type="cobiscorp.ecobis.censervicegenerator.dto.model.SGProcedureMappingParameter" id="46" index="21"><class type="cobiscorp.ecobis.censervicegenerator.dto.model.SGProcedureParameter" id="47" name="parameter"><field type="String" name="name" value="@i_p_apellido1" /><field type="String" name="dataType" value="varchar" /><field type="String" name="direction" value="in" /></class><field type="String" name="mappingTypeName" value="DTO" /><field type="String" name="mappingDirection" value="in" /><field type="String" name="dTOAlias" value="inBeneficiaryCertificateDeposit" /><field type="String" name="dTOPropertyName" value="firstSurname1" /><field type="String" name="cTSDataType" value="SQLVARCHAR" /><field type="boolean" name="allowNull" value="false" /></class><class type="cobiscorp.ecobis.censervicegenerator.dto.model.SGProcedureMappingParameter" id="48" index="22"><class type="cobiscorp.ecobis.censervicegenerator.dto.model.SGProcedureParameter" id="49" name="parameter"><field type="String" name="name" value="@i_p_apellido2" /><field type="String" name="dataType" value="varchar" /><field type="String" name="direction" value="in" /></class><field type="String" name="mappingTypeName" value="DTO" /><field type="String" name="mappingDirection" value="in" /><field type="String" name="dTOAlias" value="inBeneficiaryCertificateDeposit" /><field type="String" name="dTOPropertyName" value="firstSurname2" /><field type="String" name="cTSDataType" value="SQLVARCHAR" /><field type="boolean" name="allowNull" value="false" /></class><class type="cobiscorp.ecobis.censervicegenerator.dto.model.SGProcedureMappingParameter" id="50" index="23"><class type="cobiscorp.ecobis.censervicegenerator.dto.model.SGProcedureParameter" id="51" name="parameter"><field type="String" name="name" value="@i_p_apellido3" /><field type="String" name="dataType" value="varchar" /><field type="String" name="direction" value="in" /></class><field type="String" name="mappingTypeName" value="DTO" /><field type="String" name="mappingDirection" value="in" /><field type="String" name="dTOAlias" value="inBeneficiaryCertificateDeposit" /><field type="String" name="dTOPropertyName" value="firstSurname2" /><field type="String" name="cTSDataType" value="SQLVARCHAR" /><field type="boolean" name="allowNull" value="false" /></class><class type="cobiscorp.ecobis.censervicegenerator.dto.model.SGProcedureMappingParameter" id="52" index="24"><class type="cobiscorp.ecobis.censervicegenerator.dto.model.SGProcedureParameter" id="53" name="parameter"><field type="String" name="name" value="@i_p_apellido4" /><field type="String" name="dataType" value="varchar" /><field type="String" name="direction" value="in" /></class><field type="String" name="mappingTypeName" value="DTO" /><field type="String" name="mappingDirection" value="in" /><field type="String" name="dTOAlias" value="inBeneficiaryCertificateDeposit" /><field type="String" name="dTOPropertyName" value="firstSurname4" /><field type="String" name="cTSDataType" value="SQLVARCHAR" /><field type="boolean" name="allowNull" value="false" /></class><class type="cobiscorp.ecobis.censervicegenerator.dto.model.SGProcedureMappingParameter" id="54" index="25"><class type="cobiscorp.ecobis.censervicegenerator.dto.model.SGProcedureParameter" id="55" name="parameter"><field type="String" name="name" value="@i_parentesco1" /><field type="String" name="dataType" value="varchar" /><field type="String" name="direction" value="in" /></class><field type="String" name="mappingTypeName" value="DTO" /><field type="String" name="mappingDirection" value="in" /><field type="String" name="dTOAlias" value="inBeneficiaryCertificateDeposit" /><field type="String" name="dTOPropertyName" value="relation1" /><field type="String" name="cTSDataType" value="SQLVARCHAR" /><field type="boolean" name="allowNull" value="false" /></class><class type="cobiscorp.ecobis.censervicegenerator.dto.model.SGProcedureMappingParameter" id="56" index="26"><class type="cobiscorp.ecobis.censervicegenerator.dto.model.SGProcedureParameter" id="57" name="parameter"><field type="String" name="name" value="@i_parentesco2" /><field type="String" name="dataType" value="varchar" /><field type="String" name="direction" value="in" /></class><field type="String" name="mappingTypeName" value="DTO" /><field type="String" name="mappingDirection" value="in" /><field type="String" name="dTOAlias" value="inBeneficiaryCertificateDeposit" /><field type="String" name="dTOPropertyName" value="relation2" /><field type="String" name="cTSDataType" value="SQLVARCHAR" /><field type="boolean" name="allowNull" value="false" /></class><class type="cobiscorp.ecobis.censervicegenerator.dto.model.SGProcedureMappingParameter" id="58" index="27"><class type="cobiscorp.ecobis.censervicegenerator.dto.model.SGProcedureParameter" id="59" name="parameter"><field type="String" name="name" value="@i_parentesco3" /><field type="String" name="dataType" value="varchar" /><field type="String" name="direction" value="in" /></class><field type="String" name="mappingTypeName" value="DTO" /><field type="String" name="mappingDirection" value="in" /><field type="String" name="dTOAlias" value="inBeneficiaryCertificateDeposit" /><field type="String" name="dTOPropertyName" value="relation3" /><field type="String" name="cTSDataType" value="SQLVARCHAR" /><field type="boolean" name="allowNull" value="false" /></class><class type="cobiscorp.ecobis.censervicegenerator.dto.model.SGProcedureMappingParameter" id="60" index="28"><class type="cobiscorp.ecobis.censervicegenerator.dto.model.SGProcedureParameter" id="61" name="parameter"><field type="String" name="name" value="@i_parentesco4" /><field type="String" name="dataType" value="varchar" /><field type="String" name="direction" value="in" /></class><field type="String" name="mappingTypeName" value="DTO" /><field type="String" name="mappingDirection" value="in" /><field type="String" name="dTOAlias" value="inBeneficiaryCertificateDeposit" /><field type="String" name="dTOPropertyName" value="relation4" /><field type="String" name="cTSDataType" value="SQLVARCHAR" /><field type="boolean" name="allowNull" value="false" /></class><class type="cobiscorp.ecobis.censervicegenerator.dto.model.SGProcedureMappingParameter" id="62" index="29"><class type="cobiscorp.ecobis.censervicegenerator.dto.model.SGProcedureParameter" id="63" name="parameter"><field type="String" name="name" value="@i_periodicidad" /><field type="String" name="dataType" value="varchar" /><field type="String" name="direction" value="in" /></class><field type="String" name="mappingTypeName" value="DTO" /><field type="String" name="mappingDirection" value="in" /><field type="String" name="dTOAlias" value="inCertificateDeposit" /><field type="String" name="dTOPropertyName" value="periodicityId" /><field type="String" name="cTSDataType" value="SQLVARCHAR" /><field type="boolean" name="allowNull" value="false" /></class><class type="cobiscorp.ecobis.censervicegenerator.dto.model.SGProcedureMappingParameter" id="64" index="30"><class type="cobiscorp.ecobis.censervicegenerator.dto.model.SGProcedureParameter" id="65" name="parameter"><field type="String" name="name" value="@i_plazo" /><field type="String" name="dataType" value="int" /><field type="String" name="direction" value="in" /></class><field type="String" name="mappingTypeName" value="DTO" /><field type="String" name="mappingDirection" value="in" /><field type="String" name="dTOAlias" value="inCertificateDeposit" /><field type="String" name="dTOPropertyName" value="term" /><field type="String" name="cTSDataType" value="SQLINT4" /><field type="boolean" name="allowNull" value="false" /></class><class type="cobiscorp.ecobis.censervicegenerator.dto.model.SGProcedureMappingParameter" id="66" index="31"><class type="cobiscorp.ecobis.censervicegenerator.dto.model.SGProcedureParameter" id="67" name="parameter"><field type="String" name="name" value="@i_porcentaje1" /><field type="String" name="dataType" value="float" /><field type="String" name="direction" value="in" /></class><field type="String" name="mappingTypeName" value="DTO" /><field type="String" name="mappingDirection" value="in" /><field type="String" name="dTOAlias" value="inBeneficiaryCertificateDeposit" /><field type="String" name="dTOPropertyName" value="percentage1" /><field type="String" name="cTSDataType" value="SQLFLT8i" /><field type="boolean" name="allowNull" value="false" /></class><class type="cobiscorp.ecobis.censervicegenerator.dto.model.SGProcedureMappingParameter" id="68" index="32"><class type="cobiscorp.ecobis.censervicegenerator.dto.model.SGProcedureParameter" id="69" name="parameter"><field type="String" name="name" value="@i_porcentaje2" /><field type="String" name="dataType" value="float" /><field type="String" name="direction" value="in" /></class><field type="String" name="mappingTypeName" value="DTO" /><field type="String" name="mappingDirection" value="in" /><field type="String" name="dTOAlias" value="inBeneficiaryCertificateDeposit" /><field type="String" name="dTOPropertyName" value="percentage2" /><field type="String" name="cTSDataType" value="SQLFLT8i" /><field type="boolean" name="allowNull" value="false" /></class><class type="cobiscorp.ecobis.censervicegenerator.dto.model.SGProcedureMappingParameter" id="70" index="33"><class type="cobiscorp.ecobis.censervicegenerator.dto.model.SGProcedureParameter" id="71" name="parameter"><field type="String" name="name" value="@i_porcentaje3" /><field type="String" name="dataType" value="float" /><field type="String" name="direction" value="in" /></class><field type="String" name="mappingTypeName" value="DTO" /><field type="String" name="mappingDirection" value="in" /><field type="String" name="dTOAlias" value="inBeneficiaryCertificateDeposit" /><field type="String" name="dTOPropertyName" value="percentage3" /><field type="String" name="cTSDataType" value="SQLFLT8i" /><field type="boolean" name="allowNull" value="false" /></class><class type="cobiscorp.ecobis.censervicegenerator.dto.model.SGProcedureMappingParameter" id="72" index="34"><class type="cobiscorp.ecobis.censervicegenerator.dto.model.SGProcedureParameter" id="73" name="parameter"><field type="String" name="name" value="@i_porcentaje4" /><field type="String" name="dataType" value="float" /><field type="String" name="direction" value="in" /></class><field type="String" name="mappingTypeName" value="DTO" /><field type="String" name="mappingDirection" value="in" /><field type="String" name="dTOAlias" value="inBeneficiaryCertificateDeposit" /><field type="String" name="dTOPropertyName" value="percentage4" /><field type="String" name="cTSDataType" value="SQLFLT8i" /><field type="boolean" name="allowNull" value="false" /></class><class type="cobiscorp.ecobis.censervicegenerator.dto.model.SGProcedureMappingParameter" id="74" index="35"><class type="cobiscorp.ecobis.censervicegenerator.dto.model.SGProcedureParameter" id="75" name="parameter"><field type="String" name="name" value="@i_pro_debito" /><field type="String" name="dataType" value="int" /><field type="String" name="direction" value="in" /></class><field type="String" name="mappingTypeName" value="DTO" /><field type="String" name="mappingDirection" value="in" /><field type="String" name="dTOAlias" value="inProduct" /><field type="String" name="dTOPropertyName" value="productId" /><field type="String" name="cTSDataType" value="SQLINT4" /><field type="boolean" name="allowNull" value="false" /></class><class type="cobiscorp.ecobis.censervicegenerator.dto.model.SGProcedureMappingParameter" id="76" index="36"><class type="cobiscorp.ecobis.censervicegenerator.dto.model.SGProcedureParameter" id="77" name="parameter"><field type="String" name="name" value="@i_s_apellido1" /><field type="String" name="dataType" value="varchar" /><field type="String" name="direction" value="in" /></class><field type="String" name="mappingTypeName" value="DTO" /><field type="String" name="mappingDirection" value="in" /><field type="String" name="dTOAlias" value="inBeneficiaryCertificateDeposit" /><field type="String" name="dTOPropertyName" value="lastSurname1" /><field type="String" name="cTSDataType" value="SQLVARCHAR" /><field type="boolean" name="allowNull" value="false" /></class><class type="cobiscorp.ecobis.censervicegenerator.dto.model.SGProcedureMappingParameter" id="78" index="37"><class type="cobiscorp.ecobis.censervicegenerator.dto.model.SGProcedureParameter" id="79" name="parameter"><field type="String" name="name" value="@i_s_apellido2" /><field type="String" name="dataType" value="varchar" /><field type="String" name="direction" value="in" /></class><field type="String" name="mappingTypeName" value="DTO" /><field type="String" name="mappingDirection" value="in" /><field type="String" name="dTOAlias" value="inBeneficiaryCertificateDeposit" /><field type="String" name="dTOPropertyName" value="lastSurname2" /><field type="String" name="cTSDataType" value="SQLVARCHAR" /><field type="boolean" name="allowNull" value="false" /></class><class type="cobiscorp.ecobis.censervicegenerator.dto.model.SGProcedureMappingParameter" id="80" index="38"><class type="cobiscorp.ecobis.censervicegenerator.dto.model.SGProcedureParameter" id="81" name="parameter"><field type="String" name="name" value="@i_s_apellido3" /><field type="String" name="dataType" value="varchar" /><field type="String" name="direction" value="in" /></class><field type="String" name="mappingTypeName" value="DTO" /><field type="String" name="mappingDirection" value="in" /><field type="String" name="dTOAlias" value="inBeneficiaryCertificateDeposit" /><field type="String" name="dTOPropertyName" value="lastSurname2" /><field type="String" name="cTSDataType" value="SQLVARCHAR" /><field type="boolean" name="allowNull" value="false" /></class><class type="cobiscorp.ecobis.censervicegenerator.dto.model.SGProcedureMappingParameter" id="82" index="39"><class type="cobiscorp.ecobis.censervicegenerator.dto.model.SGProcedureParameter" id="83" name="parameter"><field type="String" name="name" value="@i_s_apellido4" /><field type="String" name="dataType" value="varchar" /><field type="String" name="direction" value="in" /></class><field type="String" name="mappingTypeName" value="DTO" /><field type="String" name="mappingDirection" value="in" /><field type="String" name="dTOAlias" value="inBeneficiaryCertificateDeposit" /><field type="String" name="dTOPropertyName" value="lastSurname4" /><field type="String" name="cTSDataType" value="SQLVARCHAR" /><field type="boolean" name="allowNull" value="false" /></class><class type="cobiscorp.ecobis.censervicegenerator.dto.model.SGProcedureMappingParameter" id="84" index="40"><class type="cobiscorp.ecobis.censervicegenerator.dto.model.SGProcedureParameter" id="85" name="parameter"><field type="String" name="name" value="@i_tasa" /><field type="String" name="dataType" value="float" /><field type="String" name="direction" value="in" /></class><field type="String" name="mappingTypeName" value="DTO" /><field type="String" name="mappingDirection" value="in" /><field type="String" name="dTOAlias" value="inCertificateDeposit" /><field type="String" name="dTOPropertyName" value="rate" /><field type="String" name="cTSDataType" value="SQLFLT8i" /><field type="boolean" name="allowNull" value="false" /></class><class type="cobiscorp.ecobis.censervicegenerator.dto.model.SGProcedureMappingParameter" id="86" index="41"><class type="cobiscorp.ecobis.censervicegenerator.dto.model.SGProcedureParameter" id="87" name="parameter"><field type="String" name="name" value="@o_retorno" /><field type="String" name="dataType" value="varchar" /><field type="String" name="direction" value="in out" /></class><field type="String" name="mappingTypeName" value="CONSTANT" /><field type="String" name="mappingDirection" value="in" /><field type="String" name="constantValue" value="AAAAAAAAAAAAAAAAAAAAAAAA" /><field type="String" name="cTSDataType" value="SQLVARCHAR" /><field type="boolean" name="allowNull" value="false" /></class><class type="cobiscorp.ecobis.censervicegenerator.dto.model.SGProcedureMappingParameter" id="88" index="42"><reference id="87" name="parameter" /><field type="String" name="mappingTypeName" value="DTO" /><field type="String" name="mappingDirection" value="out" /><field type="String" name="dTOAlias" value="outCertificateDepositResult" /><field type="String" name="dTOPropertyName" value="operationNumber" /><field type="String" name="cTSDataType" value="SQLVARCHAR" /><field type="boolean" name="allowNull" value="false" /></class><class type="cobiscorp.ecobis.censervicegenerator.dto.model.SGProcedureMappingParameter" id="89" index="43"><class type="cobiscorp.ecobis.censervicegenerator.dto.model.SGProcedureParameter" id="90" name="parameter"><field type="String" name="name" value="@i_cta" /><field type="String" name="dataType" value="varchar" /><field type="String" name="direction" value="in" /></class><field type="String" name="mappingTypeName" value="DTO" /><field type="String" name="mappingDirection" value="in" /><field type="String" name="dTOAlias" value="inProduct" /><field type="String" name="dTOPropertyName" value="productNumber" /><field type="String" name="cTSDataType" value="SQLVARCHAR" /><field type="boolean" name="allowNull" value="false" /></class><class type="cobiscorp.ecobis.censervicegenerator.dto.model.SGProcedureMappingParameter" id="91" index="44"><class type="cobiscorp.ecobis.censervicegenerator.dto.model.SGProcedureParameter" id="92" name="parameter"><field type="String" name="name" value="@i_mon" /><field type="String" name="dataType" value="tinyint" /><field type="String" name="direction" value="in" /></class><field type="String" name="mappingTypeName" value="DTO" /><field type="String" name="mappingDirection" value="in" /><field type="String" name="dTOAlias" value="inProduct" /><field type="String" name="dTOPropertyName" value="currencyId" /><field type="String" name="cTSDataType" value="SQLINT1" /><field type="boolean" name="allowNull" value="false" /></class><class type="cobiscorp.ecobis.censervicegenerator.dto.model.SGProcedureMappingParameter" id="93" index="45"><class type="cobiscorp.ecobis.censervicegenerator.dto.model.SGProcedureParameter" id="94" name="parameter"><field type="String" name="name" value="@i_prod" /><field type="String" name="dataType" value="tinyint" /><field type="String" name="direction" value="in" /></class><field type="String" name="mappingTypeName" value="DTO" /><field type="String" name="mappingDirection" value="in" /><field type="String" name="dTOAlias" value="inProduct" /><field type="String" name="dTOPropertyName" value="productId" /><field type="String" name="cTSDataType" value="SQLINT1" /><field type="boolean" name="allowNull" value="false" /></class></collection><collection type="List" length="0" id="95" name="queries"></collection><field type="String" name="trnCode" value="1801018" /><collection type="List" length="6" id="96" name="dTOs"><class type="cobiscorp.ecobis.censervicegenerator.dto.model.SGProcedureMappingDTO" id="97" index="0"><field type="String" name="dTOName" value="CertificateDeposit" /><field type="String" name="dTONamespace" value="COBISCorp.eCOBIS.InternetBanking.WebApp.Products.DTO" /><field type="String" name="dTOVersion" value="1" /><field type="int" name="repetition" value="0" /><field type="String" name="alias" value="inCertificateDeposit" /><field type="String" name="direction" value="in" /><field type="boolean" name="required" value="true" /></class><class type="cobiscorp.ecobis.censervicegenerator.dto.model.SGProcedureMappingDTO" id="98" index="1"><field type="String" name="dTOName" value="Product" /><field type="String" name="dTONamespace" value="COBISCorp.eCOBIS.InternetBanking.WebApp.Products.DTO" /><field type="String" name="dTOVersion" value="1" /><field type="int" name="repetition" value="0" /><field type="String" name="alias" value="inProduct" /><field type="String" name="direction" value="in" /><field type="boolean" name="required" value="true" /></class><class type="cobiscorp.ecobis.censervicegenerator.dto.model.SGProcedureMappingDTO" id="99" index="2"><field type="String" name="dTOName" value="User" /><field type="String" name="dTONamespace" value="COBISCorp.eCOBIS.InternetBanking.WebApp.Admin.DTO" /><field type="String" name="dTOVersion" value="1" /><field type="int" name="repetition" value="0" /><field type="String" name="alias" value="inUser" /><field type="String" name="direction" value="in" /><field type="boolean" name="required" value="true" /></class><class type="cobiscorp.ecobis.censervicegenerator.dto.model.SGProcedureMappingDTO" id="100" index="3"><field type="String" name="dTOName" value="BeneficiaryCertificateDeposit" /><field type="String" name="dTONamespace" value="COBISCorp.eCOBIS.InternetBanking.WebApp.Products.DTO" /><field type="String" name="dTOVersion" value="1" /><field type="int" name="repetition" value="0" /><field type="String" name="alias" value="inBeneficiaryCertificateDeposit" /><field type="String" name="direction" value="in" /><field type="boolean" name="required" value="true" /></class><class type="cobiscorp.ecobis.censervicegenerator.dto.model.SGProcedureMappingDTO" id="101" index="4"><field type="String" name="dTOName" value="CertificateDepositResult" /><field type="String" name="dTONamespace" value="COBISCorp.eCOBIS.InternetBanking.WebApp.Products.DTO" /><field type="String" name="dTOVersion" value="1" /><field type="int" name="repetition" value="0" /><field type="String" name="alias" value="outCertificateDepositResult" /><field type="String" name="direction" value="out" /><field type="boolean" name="required" value="true" /></class><class type="cobiscorp.ecobis.censervicegenerator.dto.model.SGProcedureMappingDTO" id="102" index="5"><field type="String" name="dTOName" value="TransactionContextCIB" /><field type="String" name="dTONamespace" value="COBISCorp.eCOBIS.InternetBanking.WebApp.Commons.DTO" /><field type="String" name="dTOVersion" value="1" /><field type="int" name="repetition" value="0" /><field type="String" name="alias" value="inTransactionContextCIB" /><field type="String" name="direction" value="in" /><field type="boolean" name="required" value="true" /></class></collection><collection type="Map" length="2" id="103" name="mappingProperties"><entry><key type="String" value="dbms" /><value type="String" value="SQLCTS" /></entry><entry><key type="String" value="CISservice" /><value type="String" value="true" /></entry></collection></class>