<class type="cobiscorp.ecobis.censervicegenerator.dto.model.SGDTO" id="1"><collection type="List" length="16" id="2" name="properties"><class type="cobiscorp.ecobis.censervicegenerator.dto.model.SGDTOProperty" id="3" index="0"><field type="String" name="name" value="id" /><field type="String" name="type" value="int" /><field type="boolean" name="isCollection" value="false" /><field type="int" name="maxLength" value="0" /><field type="boolean" name="required" value="true" /><field type="boolean" name="encrypted" value="false" /></class><class type="cobiscorp.ecobis.censervicegenerator.dto.model.SGDTOProperty" id="4" index="1"><field type="String" name="name" value="parent" /><field type="String" name="type" value="int" /><field type="boolean" name="isCollection" value="false" /><field type="int" name="maxLength" value="0" /><field type="boolean" name="required" value="true" /><field type="boolean" name="encrypted" value="false" /></class><class type="cobiscorp.ecobis.censervicegenerator.dto.model.SGDTOProperty" id="5" index="2"><field type="String" name="name" value="order" /><field type="String" name="type" value="int" /><field type="boolean" name="isCollection" value="false" /><field type="int" name="maxLength" value="0" /><field type="boolean" name="required" value="true" /><field type="boolean" name="encrypted" value="false" /></class><class type="cobiscorp.ecobis.censervicegenerator.dto.model.SGDTOProperty" id="6" index="3"><field type="String" name="name" value="level" /><field type="String" name="type" value="int" /><field type="boolean" name="isCollection" value="false" /><field type="int" name="maxLength" value="0" /><field type="boolean" name="required" value="true" /><field type="boolean" name="encrypted" value="false" /></class><class type="cobiscorp.ecobis.censervicegenerator.dto.model.SGDTOProperty" id="7" index="4"><field type="String" name="name" value="trn" /><field type="String" name="type" value="int" /><field type="boolean" name="isCollection" value="false" /><field type="int" name="maxLength" value="0" /><field type="boolean" name="required" value="true" /><field type="boolean" name="encrypted" value="false" /></class><class type="cobiscorp.ecobis.censervicegenerator.dto.model.SGDTOProperty" id="8" index="5"><field type="String" name="name" value="description" /><field type="String" name="type" value="string" /><field type="boolean" name="isCollection" value="false" /><field type="int" name="maxLength" value="0" /><field type="boolean" name="required" value="false" /><field type="boolean" name="encrypted" value="false" /></class><class type="cobiscorp.ecobis.censervicegenerator.dto.model.SGDTOProperty" id="9" index="6"><field type="String" name="name" value="file" /><field type="String" name="type" value="string" /><field type="boolean" name="isCollection" value="false" /><field type="int" name="maxLength" value="0" /><field type="boolean" name="required" value="false" /><field type="boolean" name="encrypted" value="false" /></class><class type="cobiscorp.ecobis.censervicegenerator.dto.model.SGDTOProperty" id="10" index="7"><field type="String" name="name" value="finalMenu" /><field type="String" name="type" value="string" /><field type="boolean" name="isCollection" value="false" /><field type="int" name="maxLength" value="0" /><field type="boolean" name="required" value="false" /><field type="boolean" name="encrypted" value="false" /></class><class type="cobiscorp.ecobis.censervicegenerator.dto.model.SGDTOProperty" id="11" index="8"><field type="String" name="name" value="culture" /><field type="String" name="type" value="string" /><field type="boolean" name="isCollection" value="false" /><field type="int" name="maxLength" value="0" /><field type="boolean" name="required" value="false" /><field type="boolean" name="encrypted" value="false" /></class><class type="cobiscorp.ecobis.censervicegenerator.dto.model.SGDTOProperty" id="12" index="9"><field type="String" name="name" value="favorite" /><field type="String" name="type" value="boolean" /><field type="boolean" name="isCollection" value="false" /><field type="int" name="maxLength" value="0" /><field type="boolean" name="required" value="true" /><field type="boolean" name="encrypted" value="false" /></class><class type="cobiscorp.ecobis.censervicegenerator.dto.model.SGDTOProperty" id="13" index="10"><field type="String" name="name" value="image" /><field type="String" name="type" value="string" /><field type="boolean" name="isCollection" value="false" /><field type="int" name="maxLength" value="0" /><field type="boolean" name="required" value="false" /><field type="boolean" name="encrypted" value="false" /></class><class type="cobiscorp.ecobis.censervicegenerator.dto.model.SGDTOProperty" id="14" index="11"><field type="String" name="name" value="mini" /><field type="String" name="type" value="string" /><field type="boolean" name="isCollection" value="false" /><field type="int" name="maxLength" value="0" /><field type="boolean" name="required" value="false" /><field type="boolean" name="encrypted" value="false" /></class><class type="cobiscorp.ecobis.censervicegenerator.dto.model.SGDTOProperty" id="15" index="12"><field type="String" name="name" value="favoriteDesc" /><field type="String" name="type" value="string" /><field type="boolean" name="isCollection" value="false" /><field type="int" name="maxLength" value="0" /><field type="boolean" name="required" value="false" /><field type="boolean" name="encrypted" value="false" /></class><class type="cobiscorp.ecobis.censervicegenerator.dto.model.SGDTOProperty" id="16" index="13"><field type="String" name="name" value="isPackage" /><field type="String" name="type" value="string" /><field type="boolean" name="isCollection" value="false" /><field type="int" name="maxLength" value="0" /><field type="boolean" name="required" value="false" /><field type="boolean" name="encrypted" value="false" /></class><class type="cobiscorp.ecobis.censervicegenerator.dto.model.SGDTOProperty" id="17" index="14"><field type="String" name="name" value="isNew" /><field type="String" name="type" value="string" /><field type="boolean" name="isCollection" value="false" /><field type="int" name="maxLength" value="0" /><field type="boolean" name="required" value="false" /><field type="boolean" name="encrypted" value="false" /></class><class type="cobiscorp.ecobis.censervicegenerator.dto.model.SGDTOProperty" id="18" index="15"><field type="String" name="name" value="imagePackage" /><field type="String" name="type" value="string" /><field type="boolean" name="isCollection" value="false" /><field type="int" name="maxLength" value="0" /><field type="boolean" name="required" value="false" /><field type="boolean" name="encrypted" value="false" /></class></collection><field type="String" name="name" value="MenuItem" /><collection type="List" length="0" id="19" name="templates"></collection><collection type="Map" length="0" id="20" name="templatesProperties"></collection><field type="String" name="version" value="1" /></class>