<class type="cobiscorp.ecobis.censervicegenerator.dto.model.SGDTO" id="1"><collection type="List" length="38" id="2" name="properties"><class type="cobiscorp.ecobis.censervicegenerator.dto.model.SGDTOProperty" id="3" index="0"><field type="String" name="name" value="tipo" /><field type="String" name="type" value="string" /><field type="boolean" name="isCollection" value="false" /><field type="boolean" name="required" value="false" /></class><class type="cobiscorp.ecobis.censervicegenerator.dto.model.SGDTOProperty" id="4" index="1"><field type="String" name="name" value="channel" /><field type="String" name="type" value="string" /><field type="boolean" name="isCollection" value="false" /><field type="boolean" name="required" value="false" /></class><class type="cobiscorp.ecobis.censervicegenerator.dto.model.SGDTOProperty" id="5" index="2"><field type="String" name="name" value="module" /><field type="String" name="type" value="string" /><field type="boolean" name="isCollection" value="false" /><field type="boolean" name="required" value="false" /></class><class type="cobiscorp.ecobis.censervicegenerator.dto.model.SGDTOProperty" id="6" index="3"><field type="String" name="name" value="network" /><field type="String" name="type" value="string" /><field type="boolean" name="isCollection" value="false" /><field type="boolean" name="required" value="false" /></class><class type="cobiscorp.ecobis.censervicegenerator.dto.model.SGDTOProperty" id="7" index="4"><field type="String" name="name" value="orignatingBranchCode" /><field type="String" name="type" value="string" /><field type="boolean" name="isCollection" value="false" /><field type="boolean" name="required" value="false" /></class><class type="cobiscorp.ecobis.censervicegenerator.dto.model.SGDTOProperty" id="8" index="5"><field type="String" name="name" value="office" /><field type="String" name="type" value="string" /><field type="boolean" name="isCollection" value="false" /><field type="boolean" name="required" value="false" /></class><class type="cobiscorp.ecobis.censervicegenerator.dto.model.SGDTOProperty" id="9" index="6"><field type="String" name="name" value="user" /><field type="String" name="type" value="string" /><field type="boolean" name="isCollection" value="false" /><field type="boolean" name="required" value="false" /></class><class type="cobiscorp.ecobis.censervicegenerator.dto.model.SGDTOProperty" id="10" index="7"><field type="String" name="name" value="orderType" /><field type="String" name="type" value="string" /><field type="boolean" name="isCollection" value="false" /><field type="boolean" name="required" value="false" /></class><class type="cobiscorp.ecobis.censervicegenerator.dto.model.SGDTOProperty" id="11" index="8"><field type="String" name="name" value="operationType" /><field type="String" name="type" value="string" /><field type="boolean" name="isCollection" value="false" /><field type="boolean" name="required" value="false" /></class><class type="cobiscorp.ecobis.censervicegenerator.dto.model.SGDTOProperty" id="12" index="9"><field type="String" name="name" value="orignatingAccountNumber" /><field type="String" name="type" value="string" /><field type="boolean" name="isCollection" value="false" /><field type="boolean" name="required" value="false" /></class><class type="cobiscorp.ecobis.censervicegenerator.dto.model.SGDTOProperty" id="13" index="10"><field type="String" name="name" value="orignatingCurrencyCode" /><field type="String" name="type" value="string" /><field type="boolean" name="isCollection" value="false" /><field type="boolean" name="required" value="false" /></class><class type="cobiscorp.ecobis.censervicegenerator.dto.model.SGDTOProperty" id="14" index="11"><field type="String" name="name" value="orignatingAccountProduct" /><field type="String" name="type" value="string" /><field type="boolean" name="isCollection" value="false" /><field type="boolean" name="required" value="false" /></class><class type="cobiscorp.ecobis.censervicegenerator.dto.model.SGDTOProperty" id="15" index="12"><field type="String" name="name" value="orignatingAccountType" /><field type="String" name="type" value="string" /><field type="boolean" name="isCollection" value="false" /><field type="boolean" name="required" value="false" /></class><class type="cobiscorp.ecobis.censervicegenerator.dto.model.SGDTOProperty" id="16" index="13"><field type="String" name="name" value="clientCode" /><field type="String" name="type" value="int" /><field type="boolean" name="isCollection" value="false" /><field type="boolean" name="required" value="true" /></class><class type="cobiscorp.ecobis.censervicegenerator.dto.model.SGDTOProperty" id="17" index="14"><field type="String" name="name" value="orignatingClientName" /><field type="String" name="type" value="string" /><field type="boolean" name="isCollection" value="false" /><field type="boolean" name="required" value="false" /></class><class type="cobiscorp.ecobis.censervicegenerator.dto.model.SGDTOProperty" id="18" index="15"><field type="String" name="name" value="orignatingIdentificationType" /><field type="String" name="type" value="string" /><field type="boolean" name="isCollection" value="false" /><field type="boolean" name="required" value="false" /></class><class type="cobiscorp.ecobis.censervicegenerator.dto.model.SGDTOProperty" id="19" index="16"><field type="String" name="name" value="orignatingIdentificationNum" /><field type="String" name="type" value="string" /><field type="boolean" name="isCollection" value="false" /><field type="boolean" name="required" value="false" /></class><class type="cobiscorp.ecobis.censervicegenerator.dto.model.SGDTOProperty" id="20" index="17"><field type="String" name="name" value="personType" /><field type="String" name="type" value="string" /><field type="boolean" name="isCollection" value="false" /><field type="boolean" name="required" value="false" /></class><class type="cobiscorp.ecobis.censervicegenerator.dto.model.SGDTOProperty" id="21" index="18"><field type="String" name="name" value="amount" /><field type="String" name="type" value="double" /><field type="boolean" name="isCollection" value="false" /><field type="boolean" name="required" value="true" /></class><class type="cobiscorp.ecobis.censervicegenerator.dto.model.SGDTOProperty" id="22" index="19"><field type="String" name="name" value="currencyCode" /><field type="String" name="type" value="string" /><field type="boolean" name="isCollection" value="false" /><field type="boolean" name="required" value="false" /></class><class type="cobiscorp.ecobis.censervicegenerator.dto.model.SGDTOProperty" id="23" index="20"><field type="String" name="name" value="recipientClientName" /><field type="String" name="type" value="string" /><field type="boolean" name="isCollection" value="false" /><field type="boolean" name="required" value="false" /></class><class type="cobiscorp.ecobis.censervicegenerator.dto.model.SGDTOProperty" id="24" index="21"><field type="String" name="name" value="recipientIdentificationNum" /><field type="String" name="type" value="string" /><field type="boolean" name="isCollection" value="false" /><field type="boolean" name="required" value="false" /></class><class type="cobiscorp.ecobis.censervicegenerator.dto.model.SGDTOProperty" id="25" index="22"><field type="String" name="name" value="recipientAccountNumber" /><field type="String" name="type" value="string" /><field type="boolean" name="isCollection" value="false" /><field type="boolean" name="required" value="false" /></class><class type="cobiscorp.ecobis.censervicegenerator.dto.model.SGDTOProperty" id="26" index="23"><field type="String" name="name" value="recipientMaskAccount" /><field type="String" name="type" value="string" /><field type="boolean" name="isCollection" value="false" /><field type="boolean" name="required" value="false" /></class><class type="cobiscorp.ecobis.censervicegenerator.dto.model.SGDTOProperty" id="27" index="24"><field type="String" name="name" value="recipientCodes" /><field type="String" name="type" value="string" /><field type="boolean" name="isCollection" value="false" /><field type="boolean" name="required" value="false" /></class><class type="cobiscorp.ecobis.censervicegenerator.dto.model.SGDTOProperty" id="28" index="25"><field type="String" name="name" value="description" /><field type="String" name="type" value="string" /><field type="boolean" name="isCollection" value="false" /><field type="boolean" name="required" value="false" /></class><class type="cobiscorp.ecobis.censervicegenerator.dto.model.SGDTOProperty" id="29" index="26"><field type="String" name="name" value="orignatingFunds" /><field type="String" name="type" value="string" /><field type="boolean" name="isCollection" value="false" /><field type="boolean" name="required" value="false" /></class><class type="cobiscorp.ecobis.censervicegenerator.dto.model.SGDTOProperty" id="30" index="27"><field type="String" name="name" value="destinationFunds" /><field type="String" name="type" value="string" /><field type="boolean" name="isCollection" value="false" /><field type="boolean" name="required" value="false" /></class><class type="cobiscorp.ecobis.censervicegenerator.dto.model.SGDTOProperty" id="31" index="28"><field type="String" name="name" value="etc" /><field type="String" name="type" value="string" /><field type="boolean" name="isCollection" value="false" /><field type="boolean" name="required" value="false" /></class><class type="cobiscorp.ecobis.censervicegenerator.dto.model.SGDTOProperty" id="32" index="29"><field type="String" name="name" value="feeId" /><field type="String" name="type" value="int" /><field type="boolean" name="isCollection" value="false" /><field type="boolean" name="required" value="true" /></class><class type="cobiscorp.ecobis.censervicegenerator.dto.model.SGDTOProperty" id="33" index="30"><field type="String" name="name" value="feeExceptionId" /><field type="String" name="type" value="int" /><field type="boolean" name="isCollection" value="false" /><field type="boolean" name="required" value="true" /></class><class type="cobiscorp.ecobis.censervicegenerator.dto.model.SGDTOProperty" id="34" index="31"><field type="String" name="name" value="feeDescription" /><field type="String" name="type" value="string" /><field type="boolean" name="isCollection" value="false" /><field type="boolean" name="required" value="false" /></class><class type="cobiscorp.ecobis.censervicegenerator.dto.model.SGDTOProperty" id="35" index="32"><field type="String" name="name" value="fee" /><field type="String" name="type" value="double" /><field type="boolean" name="isCollection" value="false" /><field type="boolean" name="required" value="true" /></class><class type="cobiscorp.ecobis.censervicegenerator.dto.model.SGDTOProperty" id="36" index="33"><field type="String" name="name" value="feeCurrencyCode" /><field type="String" name="type" value="string" /><field type="boolean" name="isCollection" value="false" /><field type="boolean" name="required" value="false" /></class><class type="cobiscorp.ecobis.censervicegenerator.dto.model.SGDTOProperty" id="37" index="34"><field type="String" name="name" value="country" /><field type="String" name="type" value="int" /><field type="boolean" name="isCollection" value="false" /><field type="boolean" name="required" value="true" /></class><class type="cobiscorp.ecobis.censervicegenerator.dto.model.SGDTOProperty" id="38" index="35"><field type="String" name="name" value="bankCode" /><field type="String" name="type" value="string" /><field type="boolean" name="isCollection" value="false" /><field type="boolean" name="required" value="false" /></class><class type="cobiscorp.ecobis.censervicegenerator.dto.model.SGDTOProperty" id="39" index="36"><field type="String" name="name" value="feeCausal" /><field type="String" name="type" value="int" /><field type="boolean" name="isCollection" value="false" /><field type="boolean" name="required" value="true" /></class><class type="cobiscorp.ecobis.censervicegenerator.dto.model.SGDTOProperty" id="40" index="37"><field type="String" name="name" value="tranCausal" /><field type="String" name="type" value="int" /><field type="boolean" name="isCollection" value="false" /><field type="boolean" name="required" value="true" /></class></collection><field type="String" name="name" value="ACHFeeRequest" /><collection type="List" length="0" id="41" name="templates"></collection><collection type="Map" length="0" id="42" name="templatesProperties"></collection><field type="String" name="version" value="1" /></class>