<?xml version="1.0" encoding="utf-8"?>
<DtoObject productName="COBISCorp.eCOBIS.InternetBanking.WebApp.Services.DTO" productVersion="4.6.1.0">
  <name>MT940</name>
  <nameSpace>COBISCorp.eCOBIS.InternetBanking.WebApp.Services.DTO</nameSpace>
  <javaPackage>cobiscorp.ecobis.internetbanking.webapp.services.dto</javaPackage>
  <ns>http://dto.services.webapp.internetbanking.ecobis.cobiscorp</ns>
  <TemplateProperties />
  <properties>
    <property name="sequence" propertyNet="Sequence" propertyJava="sequence" setterJavaMethod="setSequence" getterJavaMethod="getSequence" xsdType="int" netType="int" javaType="int" cobisMapping="" isInherit="false" isComplexType="false" isCollectionType="false" required="true" encrypted="false" maxLength="0" />
    <property name="line" propertyNet="Line" propertyJava="line" setterJavaMethod="setLine" getterJavaMethod="getLine" xsdType="string" netType="string" javaType="String" cobisMapping="" isInherit="false" isComplexType="false" isCollectionType="false" required="false" encrypted="false" maxLength="0" />
  </properties>
</DtoObject>