<?xml version="1.0"?>
<class type="cobiscorp.ecobis.censervicegenerator.dto.model.SGProcedureMapping" id="1">
  <class type="cobiscorp.ecobis.censervicegenerator.dto.model.SGProcedureBase" id="2" name="storedProcedure">
    <field type="String" name="database" value="cobis" />
    <field type="String" name="name" value="sp_get_colony_by_mun_api_api" />
    <field type="String" name="version" value="1" />
  </class>
  <field type="String" name="procedureName" value="cobis..sp_get_colony_by_mun_api_api" />
  <collection type="List" length="1" id="3" name="queries">
    <class type="cobiscorp.ecobis.censervicegenerator.dto.model.SGProcedureMappingQuery" id="4" index="0">
      <field type="int" name="order" value="1" />
      <field type="boolean" name="mapReturn" value="true" />
      <collection type="List" length="2" id="5" name="columns">
        <class type="cobiscorp.ecobis.censervicegenerator.dto.model.SGProcedureMappingQueryColumn" id="6" index="0">
          <field type="int" name="position" value="0" />
          <field type="String" name="columnName" value="code_colony" />
          <field type="String" name="dTOAlias" value="returnAddressTypeItems" />
          <field type="String" name="dTOPropertyName" value="code" />
          <field type="String" name="dataType" value="string" />
          <field type="String" name="format" value="" />
        </class>
        <class type="cobiscorp.ecobis.censervicegenerator.dto.model.SGProcedureMappingQueryColumn" id="7" index="1">
          <field type="int" name="position" value="1" />
          <field type="String" name="columnName" value="colony" />
          <field type="String" name="dTOAlias" value="returnAddressTypeItems" />
          <field type="String" name="dTOPropertyName" value="value" />
          <field type="String" name="dataType" value="string" />
          <field type="String" name="format" value="" />
        </class>
      </collection>
    </class>
  </collection>
  <collection type="List" length="8" id="8" name="parameters">
    <class type="cobiscorp.ecobis.censervicegenerator.dto.model.SGProcedureMappingParameter" id="9" index="0">
      <class type="cobiscorp.ecobis.censervicegenerator.dto.model.SGProcedureParameter" id="10" name="parameter">
        <field type="String" name="name" value="@i_zip_code" />
        <field type="String" name="dataType" value="varchar" />
        <field type="String" name="direction" value="in" />
      </class>
      <field type="String" name="mappingTypeName" value="DTO" />
      <field type="String" name="mappingDirection" value="in" />
      <field type="String" name="dTOAlias" value="inRequestGetColonyByMunicipality" />
      <field type="String" name="dTOPropertyName" value="zipCode" />
      <field type="String" name="cTSDataType" value="SQLVARCHAR" />
      <field type="boolean" name="allowNull" value="false" />
    </class>
    <class type="cobiscorp.ecobis.censervicegenerator.dto.model.SGProcedureMappingParameter" id="11" index="1">
      <class type="cobiscorp.ecobis.censervicegenerator.dto.model.SGProcedureParameter" id="12" name="parameter">
        <field type="String" name="name" value="@i_city_code" />
        <field type="String" name="dataType" value="varchar" />
        <field type="String" name="direction" value="in" />
      </class>
      <field type="String" name="mappingTypeName" value="DTO" />
      <field type="String" name="mappingDirection" value="in" />
      <field type="String" name="dTOAlias" value="inRequestGetColonyByMunicipality" />
      <field type="String" name="dTOPropertyName" value="municipality" />
      <field type="String" name="cTSDataType" value="SQLVARCHAR" />
      <field type="boolean" name="allowNull" value="false" />
    </class>
    <class type="cobiscorp.ecobis.censervicegenerator.dto.model.SGProcedureMappingParameter" id="13" index="2">
      <class type="cobiscorp.ecobis.censervicegenerator.dto.model.SGProcedureParameter" id="14" name="parameter">
        <field type="String" name="name" value="@o_code" />
        <field type="String" name="dataType" value="int" />
        <field type="String" name="direction" value="in out" />
      </class>
      <field type="String" name="mappingTypeName" value="CONSTANT" />
      <field type="String" name="mappingDirection" value="in" />
      <field type="String" name="constantValue" value="0" />
      <field type="String" name="cTSDataType" value="SQLINT4" />
      <field type="boolean" name="allowNull" value="false" />
    </class>
    <class type="cobiscorp.ecobis.censervicegenerator.dto.model.SGProcedureMappingParameter" id="15" index="3">
      <class type="cobiscorp.ecobis.censervicegenerator.dto.model.SGProcedureParameter" id="16" name="parameter">
        <field type="String" name="name" value="@o_code" />
        <field type="String" name="dataType" value="int" />
        <field type="String" name="direction" value="in out" />
      </class>
      <field type="String" name="mappingTypeName" value="DTO" />
      <field type="String" name="mappingDirection" value="out" />
      <field type="String" name="dTOAlias" value="outResponseGetColonyByMunicipality" />
      <field type="String" name="dTOPropertyName" value="message.code" />
      <field type="String" name="cTSDataType" value="SQLINT4" />
      <field type="boolean" name="allowNull" value="false" />
    </class>
    <class type="cobiscorp.ecobis.censervicegenerator.dto.model.SGProcedureMappingParameter" id="17" index="4">
      <class type="cobiscorp.ecobis.censervicegenerator.dto.model.SGProcedureParameter" id="18" name="parameter">
        <field type="String" name="name" value="@o_message" />
        <field type="String" name="dataType" value="varchar" />
        <field type="String" name="direction" value="in out" />
      </class>
      <field type="String" name="mappingTypeName" value="CONSTANT" />
      <field type="String" name="mappingDirection" value="in" />
      <field type="String" name="constantValue" value="XXX" />
      <field type="String" name="cTSDataType" value="SQLVARCHAR" />
      <field type="boolean" name="allowNull" value="false" />
    </class>
    <class type="cobiscorp.ecobis.censervicegenerator.dto.model.SGProcedureMappingParameter" id="19" index="5">
      <class type="cobiscorp.ecobis.censervicegenerator.dto.model.SGProcedureParameter" id="20" name="parameter">
        <field type="String" name="name" value="@o_message" />
        <field type="String" name="dataType" value="varchar" />
        <field type="String" name="direction" value="in out" />
      </class>
      <field type="String" name="mappingTypeName" value="DTO" />
      <field type="String" name="mappingDirection" value="out" />
      <field type="String" name="dTOAlias" value="outResponseGetColonyByMunicipality" />
      <field type="String" name="dTOPropertyName" value="message.message" />
      <field type="String" name="cTSDataType" value="SQLVARCHAR" />
      <field type="boolean" name="allowNull" value="false" />
    </class>
    <class type="cobiscorp.ecobis.censervicegenerator.dto.model.SGProcedureMappingParameter" id="21" index="6">
      <class type="cobiscorp.ecobis.censervicegenerator.dto.model.SGProcedureParameter" id="22" name="parameter">
        <field type="String" name="name" value="@o_success" />
        <field type="String" name="dataType" value="bit" />
        <field type="String" name="direction" value="in out" />
      </class>
      <field type="String" name="mappingTypeName" value="CONSTANT" />
      <field type="String" name="mappingDirection" value="in" />
      <field type="String" name="constantValue" value="1" />
      <field type="String" name="cTSDataType" value="SQLBIT" />
      <field type="boolean" name="allowNull" value="false" />
    </class>
    <class type="cobiscorp.ecobis.censervicegenerator.dto.model.SGProcedureMappingParameter" id="23" index="7">
      <class type="cobiscorp.ecobis.censervicegenerator.dto.model.SGProcedureParameter" id="24" name="parameter">
        <field type="String" name="name" value="@o_success" />
        <field type="String" name="dataType" value="bit" />
        <field type="String" name="direction" value="in out" />
      </class>
      <field type="String" name="mappingTypeName" value="DTO" />
      <field type="String" name="mappingDirection" value="out" />
      <field type="String" name="dTOAlias" value="outResponseGetColonyByMunicipality" />
      <field type="String" name="dTOPropertyName" value="success" />
      <field type="String" name="cTSDataType" value="SQLBIT" />
      <field type="boolean" name="allowNull" value="false" />
    </class>
  </collection>
  <collection type="List" length="0" id="25" name="parametersOpenApi">
  </collection>
  <field type="String" name="trnCode" value="18500108" />
  <collection type="List" length="3" id="26" name="dTOs">
    <class type="cobiscorp.ecobis.censervicegenerator.dto.model.SGProcedureMappingDTO" id="27" index="0">
      <field type="String" name="dTOName" value="RequestGetColonyByMunicipality" />
      <field type="String" name="dTONamespace" value="COBISCorp.eCOBIS.DataContractOperations.DTO" />
      <field type="String" name="dTOVersion" value="1" />
      <field type="int" name="repetition" value="0" />
      <field type="String" name="alias" value="inRequestGetColonyByMunicipality" />
      <field type="String" name="direction" value="in" />
      <field type="boolean" name="required" value="true" />
      <field type="String" name="stateDTO" value="" />
    </class>
    <class type="cobiscorp.ecobis.censervicegenerator.dto.model.SGProcedureMappingDTO" id="28" index="1">
      <field type="String" name="dTOName" value="ResponseGetColonyByMunicipality" />
      <field type="String" name="dTONamespace" value="COBISCorp.eCOBIS.DataContractOperations.DTO" />
      <field type="String" name="dTOVersion" value="1" />
      <field type="int" name="repetition" value="0" />
      <field type="String" name="alias" value="outResponseGetColonyByMunicipality" />
      <field type="String" name="direction" value="out" />
      <field type="boolean" name="required" value="true" />
      <field type="String" name="stateDTO" value="" />
    </class>
    <class type="cobiscorp.ecobis.censervicegenerator.dto.model.SGProcedureMappingDTO" id="29" index="2">
      <field type="String" name="dTOName" value="AddressTypeItems" />
      <field type="String" name="dTONamespace" value="COBISCorp.eCOBIS.DataContractOperations.DTO" />
      <field type="String" name="dTOVersion" value="1" />
      <field type="int" name="repetition" value="0" />
      <field type="String" name="alias" value="returnAddressTypeItems" />
      <field type="String" name="direction" value="return" />
      <field type="boolean" name="required" value="true" />
      <field type="String" name="stateDTO" value="" />
    </class>
  </collection>
  <collection type="Map" length="4" id="30" name="mappingProperties">
    <entry>
      <key type="String" value="dbms" />
      <value type="String" value="SQLCTS" />
    </entry>
    <entry>
      <key type="String" value="CISservice" />
      <value type="String" value="false" />
    </entry>
    <entry>
      <key type="String" value="Path" />
      <value type="String" value="apiOperations/onbording/getColonyByMunicipality" />
    </entry>
    <entry>
      <key type="String" value="HTTPMethod" />
      <value type="String" value="GET" />
    </entry>
  </collection>
  <field type="String" name="stateParams" value="" />
</class>