<?xml version="1.0" encoding="utf-8"?>
<procedure>
  <database>cob_bvirtual</database>
  <name>sp_campos_verif_plantillas</name>
  <type>SQLSERVER</type>
  <version>1</version>
  <parameters>
    <parameter name="@s_cliente" dataType="int" direction="in" />
    <parameter name="@i_tipo_plantilla" dataType="char" direction="in" />
    <parameter name="@i_plantilla_id" dataType="int" direction="in" />
    <parameter name="@i_arch_rec_id" dataType="int" direction="in" />
    <parameter name="@i_tipo_oper" dataType="varchar" direction="in" />
    <parameter name="@i_origen" dataType="char" direction="in" />
  </parameters>
  <queries>
    <query>
      <columns>
        <column name="COD. ARCH" />
        <column name="ENTE" />
        <column name="SEPARADOR" />
        <column name="DESTINO" />
        <column name="CABECERA" />
        <column name="TIPO PLANTILLA" />
        <column name="# CUENTAS" />
        <column name="MONEDA" />
      </columns>
      <queryText>SELECT w_id_campo_cta</queryText>
    </query>
    <query>
      <columns>
        <column name="COD. CAMPO" />
        <column name="COD. ARCHIVO" />
        <column name="COD. CAMPO PUB" />
        <column name="ORDEN" />
        <column name="TIPO LONG." />
        <column name="LONGITUD" />
        <column name="RELLENO" />
        <column name="ALINEAMIENTO" />
        <column name="DECIMALES" />
        <column name="MASCARA" />
        <column name="TOTALIZABLE" />
        <column name="LONG. MINIMA" />
        <column name="TIPO DATO" />
        <column name="OPCIONAL" />
        <column name="SIGNO" />
        <column name="DEFAULT" />
      </columns>
      <queryText>SELECT w_id_campo_prod</queryText>
    </query>
    <query>
      <columns>
        <column name="CAMPO ID" />
        <column name="VALOR" />
      </columns>
      <queryText></queryText>
    </query>
    <query>
      <columns>
        <column name="@w_id_campo_cta" />
      </columns>
      <queryText></queryText>
    </query>
    <query>
      <columns>
        <column name="@w_id_campo_prod" />
      </columns>
      <queryText></queryText>
    </query>
  </queries>
</procedure>