<?xml version="1.0" encoding="utf-8"?>
<DtoObject productName="COBISCorp.eCOBIS.InternetBanking.WebApp.Admin.DTO" productVersion="4.6.1.0">
  <name>PelRetryParameter</name>
  <nameSpace>COBISCorp.eCOBIS.InternetBanking.WebApp.Admin.DTO</nameSpace>
  <javaPackage>cobiscorp.ecobis.internetbanking.webapp.admin.dto</javaPackage>
  <ns>http://dto.admin.webapp.internetbanking.ecobis.cobiscorp</ns>
  <TemplateProperties />
  <properties>
    <property name="login" propertyNet="Login" propertyJava="login" setterJavaMethod="setLogin" getterJavaMethod="getLogin" xsdType="string" netType="string" javaType="String" cobisMapping="" isInherit="false" isComplexType="false" isCollectionType="false" required="false" encrypted="false" maxLength="0" />
    <property name="maxTrxRetry" propertyNet="MaxTrxRetry" propertyJava="maxTrxRetry" setterJavaMethod="setMaxTrxRetry" getterJavaMethod="getMaxTrxRetry" xsdType="int" netType="int" javaType="int" cobisMapping="" isInherit="false" isComplexType="false" isCollectionType="false" required="true" encrypted="false" maxLength="0" />
    <property name="messagePEL" propertyNet="MessagePEL" propertyJava="messagePEL" setterJavaMethod="setMessagePEL" getterJavaMethod="getMessagePEL" xsdType="string" netType="string" javaType="String" cobisMapping="" isInherit="false" isComplexType="false" isCollectionType="false" required="false" encrypted="false" maxLength="0" />
    <property name="resultPEL" propertyNet="ResultPEL" propertyJava="resultPEL" setterJavaMethod="setResultPEL" getterJavaMethod="isResultPEL" xsdType="boolean" netType="bool" javaType="boolean" cobisMapping="" isInherit="false" isComplexType="false" isCollectionType="false" required="true" encrypted="false" maxLength="0" />
    <property name="signatureId" propertyNet="SignatureId" propertyJava="signatureId" setterJavaMethod="setSignatureId" getterJavaMethod="getSignatureId" xsdType="long" netType="long" javaType="long" cobisMapping="" isInherit="false" isComplexType="false" isCollectionType="false" required="true" encrypted="false" maxLength="0" />
  </properties>
</DtoObject>