<class type="cobiscorp.ecobis.censervicegenerator.dto.model.SGProcedureMapping" id="1"><class type="cobiscorp.ecobis.censervicegenerator.dto.model.SGProcedureBase" id="2" name="storedProcedure"><field type="String" name="database" value="cob_bvirtual" /><field type="String" name="name" value="bv_add_transfer_batch" /><field type="String" name="version" value="1" /></class><field type="String" name="procedureName" value="cob_bvirtual..bv_add_transfer_batch" /><collection type="List" length="7" id="3" name="parameters"><class type="cobiscorp.ecobis.censervicegenerator.dto.model.SGProcedureMappingParameter" id="4" index="0"><class type="cobiscorp.ecobis.censervicegenerator.dto.model.SGProcedureParameter" id="5" name="parameter"><field type="String" name="name" value="@i_operacion" /><field type="String" name="dataType" value="char" /><field type="String" name="direction" value="in" /></class><field type="String" name="mappingTypeName" value="CONSTANT" /><field type="String" name="mappingDirection" value="in" /><field type="String" name="constantValue" value="IM" /><field type="String" name="cTSDataType" value="SQLCHAR" /><field type="boolean" name="allowNull" value="false" /></class><class type="cobiscorp.ecobis.censervicegenerator.dto.model.SGProcedureMappingParameter" id="6" index="1"><class type="cobiscorp.ecobis.censervicegenerator.dto.model.SGProcedureParameter" id="7" name="parameter"><field type="String" name="name" value="@i_login" /><field type="String" name="dataType" value="varchar" /><field type="String" name="direction" value="in" /></class><field type="String" name="mappingTypeName" value="DTO" /><field type="String" name="mappingDirection" value="in" /><field type="String" name="dTOAlias" value="inEntity" /><field type="String" name="dTOPropertyName" value="userName" /><field type="String" name="cTSDataType" value="SQLVARCHAR" /><field type="boolean" name="allowNull" value="false" /></class><class type="cobiscorp.ecobis.censervicegenerator.dto.model.SGProcedureMappingParameter" id="8" index="2"><class type="cobiscorp.ecobis.censervicegenerator.dto.model.SGProcedureParameter" id="9" name="parameter"><field type="String" name="name" value="@i_cliente" /><field type="String" name="dataType" value="int" /><field type="String" name="direction" value="in" /></class><field type="String" name="mappingTypeName" value="DTO" /><field type="String" name="mappingDirection" value="in" /><field type="String" name="dTOAlias" value="inEntity" /><field type="String" name="dTOPropertyName" value="id" /><field type="String" name="cTSDataType" value="SQLINT4" /><field type="boolean" name="allowNull" value="false" /></class><class type="cobiscorp.ecobis.censervicegenerator.dto.model.SGProcedureMappingParameter" id="10" index="3"><class type="cobiscorp.ecobis.censervicegenerator.dto.model.SGProcedureParameter" id="11" name="parameter"><field type="String" name="name" value="@i_mg_status" /><field type="String" name="dataType" value="int" /><field type="String" name="direction" value="in" /></class><field type="String" name="mappingTypeName" value="CONSTANT" /><field type="String" name="mappingDirection" value="in" /><field type="String" name="constantValue" value="9" /><field type="String" name="cTSDataType" value="SQLCHAR" /><field type="boolean" name="allowNull" value="false" /></class><class type="cobiscorp.ecobis.censervicegenerator.dto.model.SGProcedureMappingParameter" id="12" index="4"><class type="cobiscorp.ecobis.censervicegenerator.dto.model.SGProcedureParameter" id="13" name="parameter"><field type="String" name="name" value="@i_mg_type" /><field type="String" name="dataType" value="int" /><field type="String" name="direction" value="in" /></class><field type="String" name="mappingTypeName" value="CONSTANT" /><field type="String" name="mappingDirection" value="in" /><field type="String" name="constantValue" value="10" /><field type="String" name="cTSDataType" value="SQLINT4" /><field type="boolean" name="allowNull" value="false" /></class><class type="cobiscorp.ecobis.censervicegenerator.dto.model.SGProcedureMappingParameter" id="14" index="5"><class type="cobiscorp.ecobis.censervicegenerator.dto.model.SGProcedureParameter" id="15" name="parameter"><field type="String" name="name" value="@i_mg_description" /><field type="String" name="dataType" value="varchar" /><field type="String" name="direction" value="in" /></class><field type="String" name="mappingTypeName" value="DTO" /><field type="String" name="mappingDirection" value="in" /><field type="String" name="dTOAlias" value="inCondition" /><field type="String" name="dTOPropertyName" value="transactionDescription" /><field type="String" name="cTSDataType" value="SQLVARCHAR" /><field type="boolean" name="allowNull" value="true" /></class><class type="cobiscorp.ecobis.censervicegenerator.dto.model.SGProcedureMappingParameter" id="16" index="6"><class type="cobiscorp.ecobis.censervicegenerator.dto.model.SGProcedureParameter" id="17" name="parameter"><field type="String" name="name" value="@i_mg_planned_date" /><field type="String" name="dataType" value="datetime" /><field type="String" name="direction" value="in" /></class><field type="String" name="mappingTypeName" value="DTO" /><field type="String" name="mappingDirection" value="in" /><field type="String" name="dTOAlias" value="inCondition" /><field type="String" name="dTOPropertyName" value="startDate" /><field type="String" name="cTSDataType" value="SQLDATETIME" /><field type="boolean" name="allowNull" value="true" /></class></collection><collection type="List" length="1" id="18" name="queries"><class type="cobiscorp.ecobis.censervicegenerator.dto.model.SGProcedureMappingQuery" id="19" index="0"><field type="int" name="order" value="1" /><field type="boolean" name="mapReturn" value="true" /><collection type="List" length="1" id="20" name="columns"><class type="cobiscorp.ecobis.censervicegenerator.dto.model.SGProcedureMappingQueryColumn" id="21" index="0"><field type="int" name="position" value="0" /><field type="String" name="columnName" value="secuencial" /><field type="String" name="dTOAlias" value="returnSearchOption" /><field type="String" name="dTOPropertyName" value="sequential" /><field type="String" name="dataType" value="int" /><field type="String" name="format" value="" /></class></collection></class></collection><field type="String" name="trnCode" value="1800197" /><collection type="List" length="4" id="22" name="dTOs"><class type="cobiscorp.ecobis.censervicegenerator.dto.model.SGProcedureMappingDTO" id="23" index="0"><field type="String" name="dTOName" value="Condition" /><field type="String" name="dTONamespace" value="COBISCorp.eCOBIS.InternetBanking.WebApp.Admin.DTO" /><field type="String" name="dTOVersion" value="1" /><field type="int" name="repetition" value="0" /><field type="String" name="alias" value="inCondition" /><field type="String" name="direction" value="in" /><field type="boolean" name="required" value="true" /></class><class type="cobiscorp.ecobis.censervicegenerator.dto.model.SGProcedureMappingDTO" id="24" index="1"><field type="String" name="dTOName" value="SearchOption" /><field type="String" name="dTONamespace" value="COBISCorp.eCOBIS.InternetBanking.WebApp.Utils.DTO" /><field type="String" name="dTOVersion" value="1" /><field type="int" name="repetition" value="0" /><field type="String" name="alias" value="returnSearchOption" /><field type="String" name="direction" value="return" /><field type="boolean" name="required" value="true" /></class><class type="cobiscorp.ecobis.censervicegenerator.dto.model.SGProcedureMappingDTO" id="25" index="2"><field type="String" name="dTOName" value="SearchOptionCollection" /><field type="String" name="dTONamespace" value="COBISCorp.eCOBIS.InternetBanking.WebApp.Utils.DTO" /><field type="String" name="dTOVersion" value="1" /><field type="int" name="repetition" value="0" /><field type="String" name="alias" value="outSearchOptionCollection" /><field type="String" name="direction" value="out" /><field type="boolean" name="required" value="true" /></class><class type="cobiscorp.ecobis.censervicegenerator.dto.model.SGProcedureMappingDTO" id="26" index="3"><field type="String" name="dTOName" value="Entity" /><field type="String" name="dTONamespace" value="COBISCorp.eCOBIS.InternetBanking.WebApp.Admin.DTO" /><field type="String" name="dTOVersion" value="1" /><field type="int" name="repetition" value="0" /><field type="String" name="alias" value="inEntity" /><field type="String" name="direction" value="in" /><field type="boolean" name="required" value="true" /></class></collection><collection type="Map" length="3" id="27" name="mappingProperties"><entry><key type="String" value="BLIQueryPropertyName1" /><value type="String" value="searchOptions" /></entry><entry><key type="String" value="dbms" /><value type="String" value="SQLCTS" /></entry><entry><key type="String" value="CISservice" /><value type="String" value="false" /></entry></collection></class>